mpl_data_cast/__init__.py
mpl_data_cast/_version.py
mpl_data_cast/helper.py
mpl_data_cast/recipe.py
mpl_data_cast/util.py
mpl_data_cast/cli/__init__.py
mpl_data_cast/cli/__main__.py
mpl_data_cast/cli/cli.py
mpl_data_cast/gui/__init__.py
mpl_data_cast/gui/__main__.py
mpl_data_cast/gui/main.py
mpl_data_cast/gui/main.ui
mpl_data_cast/gui/preferences.py
mpl_data_cast/gui/preferences.ui
mpl_data_cast/gui/splash.py
mpl_data_cast/gui/widget_input.py
mpl_data_cast/gui/widget_output.py
mpl_data_cast/gui/widget_tree.py
mpl_data_cast/gui/widget_tree.ui
mpl_data_cast/gui/img/__init__.py
mpl_data_cast/gui/img/mpldc_icon.png
mpl_data_cast/mod_recipes/__init__.py
mpl_data_cast/mod_recipes/rcp_catchall.py
mpl_data_cast/mod_recipes/rcp_oah.py
mpl_data_cast/mod_recipes/rcp_qlsi.py
mpl_data_cast/mod_recipes/rcp_rtdc.py
mpl_data_cast-0.7.7.dist-info/licenses/LICENSE
mpl_data_cast-0.7.7.dist-info/METADATA
mpl_data_cast-0.7.7.dist-info/WHEEL
mpl_data_cast-0.7.7.dist-info/entry_points.txt
mpl_data_cast-0.7.7.dist-info/top_level.txt
mpl_data_cast-0.7.7.dist-info/RECORD
