Metadata-Version: 2.4
Name: mpl_data_cast
Version: 0.7.7
Summary: convert and transfer data to network shares
Author: Benedikt Hartmann, Paul Müller
Maintainer-email: Paul Müller <dev@craban.de>
License: GPL v3
Project-URL: source, https://github.com/GuckLab/MPL-Data-Cast
Project-URL: tracker, https://github.com/GuckLab/MPL-Data-Cast/issues
Project-URL: documentation, https://mpl-data-cast.readthedocs.io
Project-URL: changelog, https://github.com/GuckLab/MPL-Data-Cast/blob/main/CHANGELOG
Keywords: Data maintenance,MPL,Max Planck
Classifier: Operating System :: OS Independent
Classifier: Programming Language :: Python :: 3
Classifier: Intended Audience :: Science/Research
Requires-Python: <4,>=3.10
License-File: LICENSE
Requires-Dist: click>=8
Requires-Dist: dclab>=0.62.11
Requires-Dist: h5py>=3.8.0
Requires-Dist: hdf5plugin
Requires-Dist: numpy>=1.21
Requires-Dist: psutil
Requires-Dist: pyqt6
Requires-Dist: tifffile==2022.3.16
Dynamic: license-file
